erroraffirmations/__init__.py
erroraffirmations/_version.py
erroraffirmations/affirmations.py
erroraffirmations/data/affirmations.txt
erroraffirmations-0.1.0.dist-info/LICENSE
erroraffirmations-0.1.0.dist-info/METADATA
erroraffirmations-0.1.0.dist-info/WHEEL
erroraffirmations-0.1.0.dist-info/top_level.txt
erroraffirmations-0.1.0.dist-info/zip-safe
erroraffirmations-0.1.0.dist-info/RECORD
