Metadata-Version: 2.1
Name: erroraffirmations
Version: 0.1.0
Summary: Affirmative error messages for Python
Author-email: Thomas Gessey-Jones <thomasgesseyjones@gmail.com>
Maintainer-email: Thomas Gessey-Jones <thomasgesseyjones@gmail.com>
License: MIT License
Project-URL: Homepage, https://github.com/ThomasGesseyJones/ErrorAffirmations
Project-URL: Bug Tracker, https://github.com/ThomasGesseyJones/ErrorAffirmations/issues
Classifier: Programming Language :: Python :: 3
Classifier: Operating System :: OS Independent
Classifier: Development Status :: 4 - Beta
Classifier: Natural Language :: English
Classifier: Topic :: Software Development :: Bug Tracking
Requires-Python: >=3.7
License-File: LICENSE
Provides-Extra: docs
Requires-Dist: sphinx ; extra == 'docs'
Requires-Dist: sphinx-rtd-theme ; extra == 'docs'
Requires-Dist: numpydoc ; extra == 'docs'
Provides-Extra: test
Requires-Dist: packaging ; extra == 'test'
Requires-Dist: flake8 ; extra == 'test'
Requires-Dist: pydocstyle ; extra == 'test'
Requires-Dist: pytest ; extra == 'test'
Requires-Dist: pytest-cov ; extra == 'test'
Requires-Dist: pre-commit ; extra == 'test'
